pyvisgen/__init__.py
pyvisgen/_plugin_manager.py
pyvisgen/_version.py
pyvisgen/version.py
pyvisgen/dataset/__init__.py
pyvisgen/dataset/dataset.py
pyvisgen/dataset/utils.py
pyvisgen/fits/__init__.py
pyvisgen/fits/data.py
pyvisgen/fits/writer.py
pyvisgen/io/__init__.py
pyvisgen/io/config.py
pyvisgen/io/datawriters.py
pyvisgen/layouts/__init__.py
pyvisgen/layouts/layouts.py
pyvisgen/simulation/__init__.py
pyvisgen/simulation/array.py
pyvisgen/simulation/observation.py
pyvisgen/simulation/scan.py
pyvisgen/simulation/utils.py
pyvisgen/simulation/visibility.py
pyvisgen/tools/__init__.py
pyvisgen/tools/cli.py
pyvisgen/tools/create_dataset.py
pyvisgen/tools/quickstart.py
pyvisgen/utils/__init__.py
pyvisgen/utils/batch_size.py
pyvisgen/utils/carbon_tracking.py
pyvisgen/utils/data.py
pyvisgen/utils/logging.py
pyvisgen-0.7.2.data/data/share/configs/default_data_set.toml
pyvisgen-0.7.2.data/data/share/resources/layouts/alma.txt
pyvisgen-0.7.2.data/data/share/resources/layouts/alma_dsharp.txt
pyvisgen-0.7.2.data/data/share/resources/layouts/dsa2000W.txt
pyvisgen-0.7.2.data/data/share/resources/layouts/dsa2000_31b.txt
pyvisgen-0.7.2.data/data/share/resources/layouts/eht.txt
pyvisgen-0.7.2.data/data/share/resources/layouts/meerkat.txt
pyvisgen-0.7.2.data/data/share/resources/layouts/meerkat_test.txt
pyvisgen-0.7.2.data/data/share/resources/layouts/vla.txt
pyvisgen-0.7.2.data/data/share/resources/layouts/vlba.txt
pyvisgen-0.7.2.data/data/share/resources/layouts/vlba_light.txt
pyvisgen-0.7.2.dist-info/METADATA
pyvisgen-0.7.2.dist-info/WHEEL
pyvisgen-0.7.2.dist-info/entry_points.txt
pyvisgen-0.7.2.dist-info/licenses/LICENSE
pyvisgen-0.7.2.dist-info/RECORD
