Metadata-Version: 2.4
Name: pyvisgen
Version: 0.7.2
Summary: Simulate radio interferometer observations and visibility generation with the RIME formalism.
Author: Felix Geyer, Stefan Fröse
Author-email: Kevin Schmitz <kevin2.schmitz@tu-dortmund.de>, Anno Knierim <anno.knierim@tu-dortmund.de>, Tom Groß <tom.gross@tu-dortmund.de>
Maintainer-email: Kevin Schmitz <kevin2.schmitz@tu-dortmund.de>, Anno Knierim <anno.knierim@tu-dortmund.de>, Tom Groß <tom.gross@tu-dortmund.de>
License: MIT
License-File: LICENSE
Classifier: Development Status :: 4 - Beta
Classifier: Intended Audience :: Science/Research
Classifier: License :: OSI Approved :: MIT License
Classifier: Programming Language :: Python :: 3
Classifier: Programming Language :: Python :: 3.11
Classifier: Programming Language :: Python :: 3.12
Classifier: Topic :: Scientific/Engineering :: Astronomy
Classifier: Topic :: Scientific/Engineering :: Information Analysis
Classifier: Topic :: Scientific/Engineering :: Physics
Requires-Python: >=3.11
Requires-Dist: astropy<=6.1.0
Requires-Dist: click
Requires-Dist: h5py
Requires-Dist: joblib
Requires-Dist: natsort
Requires-Dist: numpy
Requires-Dist: pandas
Requires-Dist: pydantic>=2.12.3
Requires-Dist: pyvisgrid
Requires-Dist: radioft
Requires-Dist: rich
Requires-Dist: rich-click>=1.8.9
Requires-Dist: scipy
Requires-Dist: toml
Requires-Dist: torch
Requires-Dist: tqdm
Provides-Extra: all
Requires-Dist: codecarbon; extra == 'all'
Requires-Dist: matplotlib; extra == 'all'
Requires-Dist: pyarrow; extra == 'all'
Requires-Dist: pytorch-finufft; extra == 'all'
Requires-Dist: webdataset; extra == 'all'
Provides-Extra: codecarbon
Requires-Dist: codecarbon; extra == 'codecarbon'
Provides-Extra: plot
Requires-Dist: matplotlib; extra == 'plot'
Provides-Extra: tutorials
Requires-Dist: matplotlib; extra == 'tutorials'
Requires-Dist: pytorch-finufft; extra == 'tutorials'
Provides-Extra: webdataset
Requires-Dist: pyarrow; extra == 'webdataset'
Requires-Dist: webdataset; extra == 'webdataset'
